swig/__init__.py
swig/_version.py
swig/data/bin/swig.exe
swig/data/share/swig/4.2.0/allkw.swg
swig/data/share/swig/4.2.0/attribute.i
swig/data/share/swig/4.2.0/carrays.i
swig/data/share/swig/4.2.0/cdata.i
swig/data/share/swig/4.2.0/cmalloc.i
swig/data/share/swig/4.2.0/constraints.i
swig/data/share/swig/4.2.0/cpointer.i
swig/data/share/swig/4.2.0/cstring.i
swig/data/share/swig/4.2.0/cwstring.i
swig/data/share/swig/4.2.0/director_common.swg
swig/data/share/swig/4.2.0/exception.i
swig/data/share/swig/4.2.0/intrusive_ptr.i
swig/data/share/swig/4.2.0/inttypes.i
swig/data/share/swig/4.2.0/javascriptkw.swg
swig/data/share/swig/4.2.0/linkruntime.c
swig/data/share/swig/4.2.0/math.i
swig/data/share/swig/4.2.0/runtime.swg
swig/data/share/swig/4.2.0/shared_ptr.i
swig/data/share/swig/4.2.0/std_except.i
swig/data/share/swig/4.2.0/stdint.i
swig/data/share/swig/4.2.0/stl.i
swig/data/share/swig/4.2.0/swig.swg
swig/data/share/swig/4.2.0/swigarch.i
swig/data/share/swig/4.2.0/swigerrors.swg
swig/data/share/swig/4.2.0/swigfragments.swg
swig/data/share/swig/4.2.0/swiginit.swg
swig/data/share/swig/4.2.0/swiglabels.swg
swig/data/share/swig/4.2.0/swigrun.i
swig/data/share/swig/4.2.0/swigrun.swg
swig/data/share/swig/4.2.0/swigwarn.swg
swig/data/share/swig/4.2.0/swigwarnings.swg
swig/data/share/swig/4.2.0/wchar.i
swig/data/share/swig/4.2.0/windows.i
swig/data/share/swig/4.2.0/csharp/argcargv.i
swig/data/share/swig/4.2.0/csharp/arrays_csharp.i
swig/data/share/swig/4.2.0/csharp/boost_intrusive_ptr.i
swig/data/share/swig/4.2.0/csharp/boost_shared_ptr.i
swig/data/share/swig/4.2.0/csharp/complex.i
swig/data/share/swig/4.2.0/csharp/csharp.swg
swig/data/share/swig/4.2.0/csharp/csharphead.swg
swig/data/share/swig/4.2.0/csharp/csharpkw.swg
swig/data/share/swig/4.2.0/csharp/director.swg
swig/data/share/swig/4.2.0/csharp/enums.swg
swig/data/share/swig/4.2.0/csharp/enumsimple.swg
swig/data/share/swig/4.2.0/csharp/enumtypesafe.swg
swig/data/share/swig/4.2.0/csharp/std_array.i
swig-4.2.0.post0.dist-info/LICENSE
swig-4.2.0.post0.dist-info/LICENSE-GPL
swig-4.2.0.post0.dist-info/LICENSE-SWIG
swig-4.2.0.post0.dist-info/LICENSE-UNIVERSITIES
swig-4.2.0.post0.dist-info/METADATA
swig-4.2.0.post0.dist-info/WHEEL
swig-4.2.0.post0.dist-info/entry_points.txt
swig-4.2.0.post0.dist-info/top_level.txt
swig-4.2.0.post0.dist-info/RECORD
