Metadata-Version: 2.1
Name: swig
Version: 4.2.0.post0
Summary: SWIG is a software development tool that connects programs written in C and C++ with a variety of high-level programming languages.
License: https://github.com/swig/swig/blob/master/LICENSE
Project-URL: Homepage, https://swig.org/
Project-URL: Download, https://swig.org/download.html
Project-URL: Source Code, https://github.com/nightlark/swig-pypi
Project-URL: Bug Tracker, https://github.com/nightlark/swig-pypi/issues
Keywords: swig,build,c,c++
Classifier: License :: OSI Approved :: GNU General Public License v3 or later (GPLv3+)
Classifier: License :: Other/Proprietary License
Classifier: Programming Language :: C
Classifier: Programming Language :: C++
Classifier: Programming Language :: Python
Classifier: Operating System :: OS Independent
Classifier: Development Status :: 5 - Production/Stable
Classifier: Intended Audience :: Developers
Classifier: Topic :: Software Development :: Build Tools
License-File: LICENSE
License-File: LICENSE-GPL
License-File: LICENSE-SWIG
License-File: LICENSE-UNIVERSITIES
